[{
  "dateTime" : "08/14/18 00:00:00",
  "value" : "724"
},{
  "dateTime" : "08/15/18 00:00:00",
  "value" : "713"
},{
  "dateTime" : "08/16/18 00:00:00",
  "value" : "758"
},{
  "dateTime" : "08/17/18 00:00:00",
  "value" : "667"
},{
  "dateTime" : "08/18/18 00:00:00",
  "value" : "762"
},{
  "dateTime" : "08/19/18 00:00:00",
  "value" : "1179"
},{
  "dateTime" : "08/20/18 00:00:00",
  "value" : "1260"
},{
  "dateTime" : "08/21/18 00:00:00",
  "value" : "795"
},{
  "dateTime" : "08/22/18 00:00:00",
  "value" : "638"
},{
  "dateTime" : "08/23/18 00:00:00",
  "value" : "703"
},{
  "dateTime" : "08/24/18 00:00:00",
  "value" : "798"
},{
  "dateTime" : "08/25/18 00:00:00",
  "value" : "483"
},{
  "dateTime" : "08/26/18 00:00:00",
  "value" : "745"
},{
  "dateTime" : "08/27/18 00:00:00",
  "value" : "629"
},{
  "dateTime" : "08/28/18 00:00:00",
  "value" : "954"
},{
  "dateTime" : "08/29/18 00:00:00",
  "value" : "657"
},{
  "dateTime" : "08/30/18 00:00:00",
  "value" : "699"
},{
  "dateTime" : "08/31/18 00:00:00",
  "value" : "640"
},{
  "dateTime" : "09/01/18 00:00:00",
  "value" : "666"
},{
  "dateTime" : "09/02/18 00:00:00",
  "value" : "642"
},{
  "dateTime" : "09/03/18 00:00:00",
  "value" : "491"
},{
  "dateTime" : "09/04/18 00:00:00",
  "value" : "728"
},{
  "dateTime" : "09/05/18 00:00:00",
  "value" : "601"
},{
  "dateTime" : "09/06/18 00:00:00",
  "value" : "816"
},{
  "dateTime" : "09/07/18 00:00:00",
  "value" : "1225"
},{
  "dateTime" : "09/08/18 00:00:00",
  "value" : "833"
},{
  "dateTime" : "09/09/18 00:00:00",
  "value" : "608"
},{
  "dateTime" : "09/10/18 00:00:00",
  "value" : "698"
},{
  "dateTime" : "09/11/18 00:00:00",
  "value" : "761"
},{
  "dateTime" : "09/12/18 00:00:00",
  "value" : "655"
}]