[{
  "logId" : 1480809599000,
  "weight" : 136.2,
  "bmi" : 24.13,
  "date" : "12/03/16",
  "time" : "23:59:59",
  "source" : "API"
},{
  "logId" : 1480895999000,
  "weight" : 136.2,
  "bmi" : 24.13,
  "date" : "12/04/16",
  "time" : "23:59:59",
  "source" : "API"
},{
  "logId" : 1481155199000,
  "weight" : 134.8,
  "bmi" : 23.88,
  "date" : "12/07/16",
  "time" : "23:59:59",
  "source" : "API"
},{
  "logId" : 1481414399000,
  "weight" : 135.2,
  "bmi" : 23.96,
  "date" : "12/10/16",
  "time" : "23:59:59",
  "source" : "API"
},{
  "logId" : 1481500799000,
  "weight" : 134.1,
  "bmi" : 23.76,
  "date" : "12/11/16",
  "time" : "23:59:59",
  "source" : "API"
},{
  "logId" : 1481587199000,
  "weight" : 134.1,
  "bmi" : 23.76,
  "date" : "12/12/16",
  "time" : "23:59:59",
  "source" : "API"
},{
  "logId" : 1481846399000,
  "weight" : 136.0,
  "bmi" : 24.1,
  "date" : "12/15/16",
  "time" : "23:59:59",
  "source" : "API"
},{
  "logId" : 1481932799000,
  "weight" : 136.4,
  "bmi" : 24.18,
  "date" : "12/16/16",
  "time" : "23:59:59",
  "source" : "API"
},{
  "logId" : 1482019199000,
  "weight" : 134.7,
  "bmi" : 23.87,
  "date" : "12/17/16",
  "time" : "23:59:59",
  "source" : "API"
},{
  "logId" : 1482105599000,
  "weight" : 134.3,
  "bmi" : 23.8,
  "date" : "12/18/16",
  "time" : "23:59:59",
  "source" : "API"
},{
  "logId" : 1482191999000,
  "weight" : 133.9,
  "bmi" : 23.73,
  "date" : "12/19/16",
  "time" : "23:59:59",
  "source" : "API"
},{
  "logId" : 1482278399000,
  "weight" : 134.5,
  "bmi" : 23.83,
  "date" : "12/20/16",
  "time" : "23:59:59",
  "source" : "API"
}]