[{
  "logId" : 1536824983000,
  "weight" : 134.2,
  "bmi" : 23.79,
  "fat" : 31.823999404907227,
  "date" : "09/13/18",
  "time" : "07:49:43",
  "source" : "Aria"
},{
  "logId" : 1536914945000,
  "weight" : 132.7,
  "bmi" : 23.52,
  "fat" : 31.67799949645996,
  "date" : "09/14/18",
  "time" : "08:49:05",
  "source" : "Aria"
},{
  "logId" : 1537004823000,
  "weight" : 132.7,
  "bmi" : 23.52,
  "fat" : 31.5310001373291,
  "date" : "09/15/18",
  "time" : "09:47:03",
  "source" : "Aria"
},{
  "logId" : 1537173232000,
  "weight" : 133.1,
  "bmi" : 23.6,
  "fat" : 31.256999969482422,
  "date" : "09/17/18",
  "time" : "08:33:52",
  "source" : "Aria"
},{
  "logId" : 1537256016000,
  "weight" : 133.1,
  "bmi" : 23.6,
  "fat" : 31.201000213623047,
  "date" : "09/18/18",
  "time" : "07:33:36",
  "source" : "Aria"
},{
  "logId" : 1537347662000,
  "weight" : 133.1,
  "bmi" : 23.6,
  "fat" : 31.17300033569336,
  "date" : "09/19/18",
  "time" : "09:01:02",
  "source" : "Aria"
},{
  "logId" : 1537430280000,
  "weight" : 132.2,
  "bmi" : 23.44,
  "fat" : 31.224000930786133,
  "date" : "09/20/18",
  "time" : "07:58:00",
  "source" : "Aria"
},{
  "logId" : 1537517993000,
  "weight" : 132.2,
  "bmi" : 23.44,
  "fat" : 31.194000244140625,
  "date" : "09/21/18",
  "time" : "08:19:53",
  "source" : "Aria"
},{
  "logId" : 1537781600000,
  "weight" : 133.6,
  "bmi" : 23.69,
  "fat" : 30.67300033569336,
  "date" : "09/24/18",
  "time" : "09:33:20",
  "source" : "Aria"
},{
  "logId" : 1537953435000,
  "weight" : 133.6,
  "bmi" : 23.69,
  "fat" : 30.55500030517578,
  "date" : "09/26/18",
  "time" : "09:17:15",
  "source" : "Aria"
},{
  "logId" : 1538035831000,
  "weight" : 132.8,
  "bmi" : 23.55,
  "fat" : 30.409000396728516,
  "date" : "09/27/18",
  "time" : "08:10:31",
  "source" : "Aria"
},{
  "logId" : 1538127441000,
  "weight" : 132.6,
  "bmi" : 23.5,
  "fat" : 30.798999786376953,
  "date" : "09/28/18",
  "time" : "09:37:21",
  "source" : "Aria"
},{
  "logId" : 1538294466000,
  "weight" : 133.1,
  "bmi" : 23.6,
  "fat" : 30.677000045776367,
  "date" : "09/30/18",
  "time" : "08:01:06",
  "source" : "Aria"
},{
  "logId" : 1538382211000,
  "weight" : 133.1,
  "bmi" : 23.6,
  "fat" : 30.68400001525879,
  "date" : "10/01/18",
  "time" : "08:23:31",
  "source" : "Aria"
},{
  "logId" : 1538466332000,
  "weight" : 133.6,
  "bmi" : 23.68,
  "fat" : 30.69499969482422,
  "date" : "10/02/18",
  "time" : "07:45:32",
  "source" : "Aria"
},{
  "logId" : 1538558306000,
  "weight" : 132.8,
  "bmi" : 23.53,
  "fat" : 30.47100067138672,
  "date" : "10/03/18",
  "time" : "09:18:26",
  "source" : "Aria"
},{
  "logId" : 1538733637000,
  "weight" : 131.6,
  "bmi" : 23.33,
  "fat" : 30.533000946044922,
  "date" : "10/05/18",
  "time" : "10:00:37",
  "source" : "Aria"
},{
  "logId" : 1538989911000,
  "weight" : 132.5,
  "bmi" : 23.48,
  "fat" : 30.367000579833984,
  "date" : "10/08/18",
  "time" : "09:11:51",
  "source" : "Aria"
},{
  "logId" : 1539071024000,
  "weight" : 132.5,
  "bmi" : 23.48,
  "fat" : 30.273000717163086,
  "date" : "10/09/18",
  "time" : "07:43:44",
  "source" : "Aria"
},{
  "logId" : 1539164588000,
  "weight" : 130.9,
  "bmi" : 23.2,
  "fat" : 30.075000762939453,
  "date" : "10/10/18",
  "time" : "09:43:08",
  "source" : "Aria"
}]